Workbook

Sheet Resumen General
B2: SISTEMA DE CONTROL DE VENTAS E INVENTARIO - IPHONE
B3: VENTAS TOTALES | D3: INVERSIÓN TOTAL | F3: UTILIDAD EN VENTAS | H3: STOCK DISPONIBLE | J3: MARGEN PROMEDIO
B4: =H34 -> 0 | D4: =G34 -> 0 | F4: =I34 -> 0 | H4: =F34 -> 0 | J4: =IF(B4>0, F4/B4, 0) -> 0
B5: Ingresos por ventas acumuladas | D5: Costo de compras realizadas | F5: Ganancia sobre unidades vendidas | H5: Unidades actuales en almacén | J5: Rentabilidad bruta estimada
B7: Producto | C7: Categoría | D7: Entradas | E7: Salidas | F7: Stock Actual | G7: Costo Total ($) | H7: Ventas Total ($) | I7: Ganancia Neta ($) | J7: Estado Stock
B8: ='Catálogo'!A2 -> iPhone 16 Pro Max | C8: ='Catálogo'!B2 -> Serie 16 Pro | D8: =SUMIF('Stock de Entrada'!$C$2:$C$500, B8, 'Stock de Entrada'!$D$2:$D$500) -> 0 | E8: =SUMIF('Stock de Vendidos'!$C$2:$C$500, B8, 'Stock de Vendidos'!$D$2:$D$500) -> 0 | F8: =D8-E8 -> 0 | G8: =SUMIF('Stock de Entrada'!$C$2:$C$500, B8, 'Stock de Entrada'!$I$2:$I$500) -> 0 | H8: =SUMIF('Stock de Vendidos'!$C$2:$C$500, B8, 'Stock de Vendidos'!$I$2:$I$500) -> 0 | I8: =IF(D8>0, H8 - (E8 * (G8 / D8)), 0) -> 0 | J8: =IF(F8<=0, "Agotado", IF(F8<=3, "Stock Bajo", "Disponible")) -> Agotado
B9: ='Catálogo'!A3 -> iPhone 16 Pro | C9: ='Catálogo'!B3 -> Serie 16 Pro | D9: =SUMIF('Stock de Entrada'!$C$2:$C$500, B9, 'Stock de Entrada'!$D$2:$D$500) -> 0 | E9: =SUMIF('Stock de Vendidos'!$C$2:$C$500, B9, 'Stock de Vendidos'!$D$2:$D$500) -> 0 | F9: =D9-E9 -> 0 | G9: =SUMIF('Stock de Entrada'!$C$2:$C$500, B9, 'Stock de Entrada'!$I$2:$I$500) -> 0 | H9: =SUMIF('Stock de Vendidos'!$C$2:$C$500, B9, 'Stock de Vendidos'!$I$2:$I$500) -> 0 | I9: =IF(D9>0, H9 - (E9 * (G9 / D9)), 0) -> 0 | J9: =IF(F9<=0, "Agotado", IF(F9<=3, "Stock Bajo", "Disponible")) -> Agotado
B10: ='Catálogo'!A4 -> iPhone 16 Plus | C10: ='Catálogo'!B4 -> Serie 16 Estándar | D10: =SUMIF('Stock de Entrada'!$C$2:$C$500, B10, 'Stock de Entrada'!$D$2:$D$500) -> 0 | E10: =SUMIF('Stock de Vendidos'!$C$2:$C$500, B10, 'Stock de Vendidos'!$D$2:$D$500) -> 0 | F10: =D10-E10 -> 0 | G10: =SUMIF('Stock de Entrada'!$C$2:$C$500, B10, 'Stock de Entrada'!$I$2:$I$500) -> 0 | H10: =SUMIF('Stock de Vendidos'!$C$2:$C$500, B10, 'Stock de Vendidos'!$I$2:$I$500) -> 0 | I10: =IF(D10>0, H10 - (E10 * (G10 / D10)), 0) -> 0 | J10: =IF(F10<=0, "Agotado", IF(F10<=3, "Stock Bajo", "Disponible")) -> Agotado
B11: ='Catálogo'!A5 -> iPhone 16 | C11: ='Catálogo'!B5 -> Serie 16 Estándar | D11: =SUMIF('Stock de Entrada'!$C$2:$C$500, B11, 'Stock de Entrada'!$D$2:$D$500) -> 0 | E11: =SUMIF('Stock de Vendidos'!$C$2:$C$500, B11, 'Stock de Vendidos'!$D$2:$D$500) -> 0 | F11: =D11-E11 -> 0 | G11: =SUMIF('Stock de Entrada'!$C$2:$C$500, B11, 'Stock de Entrada'!$I$2:$I$500) -> 0 | H11: =SUMIF('Stock de Vendidos'!$C$2:$C$500, B11, 'Stock de Vendidos'!$I$2:$I$500) -> 0 | I11: =IF(D11>0, H11 - (E11 * (G11 / D11)), 0) -> 0 | J11: =IF(F11<=0, "Agotado", IF(F11<=3, "Stock Bajo", "Disponible")) -> Agotado
B12: ='Catálogo'!A6 -> iPhone 16e | C12: ='Catálogo'!B6 -> Serie 16 Estándar | D12: =SUMIF('Stock de Entrada'!$C$2:$C$500, B12, 'Stock de Entrada'!$D$2:$D$500) -> 0 | E12: =SUMIF('Stock de Vendidos'!$C$2:$C$500, B12, 'Stock de Vendidos'!$D$2:$D$500) -> 0 | F12: =D12-E12 -> 0 | G12: =SUMIF('Stock de Entrada'!$C$2:$C$500, B12, 'Stock de Entrada'!$I$2:$I$500) -> 0 | H12: =SUMIF('Stock de Vendidos'!$C$2:$C$500, B12, 'Stock de Vendidos'!$I$2:$I$500) -> 0 | I12: =IF(D12>0, H12 - (E12 * (G12 / D12)), 0) -> 0 | J12: =IF(F12<=0, "Agotado", IF(F12<=3, "Stock Bajo", "Disponible")) -> Agotado
B13: ='Catálogo'!A7 -> iPhone 15 Pro Max | C13: ='Catálogo'!B7 -> Serie 15 Pro | D13: =SUMIF('Stock de Entrada'!$C$2:$C$500, B13, 'Stock de Entrada'!$D$2:$D$500) -> 0 | E13: =SUMIF('Stock de Vendidos'!$C$2:$C$500, B13, 'Stock de Vendidos'!$D$2:$D$500) -> 0 | F13: =D13-E13 -> 0 | G13: =SUMIF('Stock de Entrada'!$C$2:$C$500, B13, 'Stock de Entrada'!$I$2:$I$500) -> 0 | H13: =SUMIF('Stock de Vendidos'!$C$2:$C$500, B13, 'Stock de Vendidos'!$I$2:$I$500) -> 0 | I13: =IF(D13>0, H13 - (E13 * (G13 / D13)), 0) -> 0 | J13: =IF(F13<=0, "Agotado", IF(F13<=3, "Stock Bajo", "Disponible")) -> Agotado
B14: ='Catálogo'!A8 -> iPhone 15 Pro | C14: ='Catálogo'!B8 -> Serie 15 Pro | D14: =SUMIF('Stock de Entrada'!$C$2:$C$500, B14, 'Stock de Entrada'!$D$2:$D$500) -> 0 | E14: =SUMIF('Stock de Vendidos'!$C$2:$C$500, B14, 'Stock de Vendidos'!$D$2:$D$500) -> 0 | F14: =D14-E14 -> 0 | G14: =SUMIF('Stock de Entrada'!$C$2:$C$500, B14, 'Stock de Entrada'!$I$2:$I$500) -> 0 | H14: =SUMIF('Stock de Vendidos'!$C$2:$C$500, B14, 'Stock de Vendidos'!$I$2:$I$500) -> 0 | I14: =IF(D14>0, H14 - (E14 * (G14 / D14)), 0) -> 0 | J14: =IF(F14<=0, "Agotado", IF(F14<=3, "Stock Bajo", "Disponible")) -> Agotado
B15: ='Catálogo'!A9 -> iPhone 15 Plus | C15: ='Catálogo'!B9 -> Serie 15 Estándar | D15: =SUMIF('Stock de Entrada'!$C$2:$C$500, B15, 'Stock de Entrada'!$D$2:$D$500) -> 0 | E15: =SUMIF('Stock de Vendidos'!$C$2:$C$500, B15, 'Stock de Vendidos'!$D$2:$D$500) -> 0 | F15: =D15-E15 -> 0 | G15: =SUMIF('Stock de Entrada'!$C$2:$C$500, B15, 'Stock de Entrada'!$I$2:$I$500) -> 0 | H15: =SUMIF('Stock de Vendidos'!$C$2:$C$500, B15, 'Stock de Vendidos'!$I$2:$I$500) -> 0 | I15: =IF(D15>0, H15 - (E15 * (G15 / D15)), 0) -> 0 | J15: =IF(F15<=0, "Agotado", IF(F15<=3, "Stock Bajo", "Disponible")) -> Agotado
B16: ='Catálogo'!A10 -> iPhone 15 | C16: ='Catálogo'!B10 -> Serie 15 Estándar | D16: =SUMIF('Stock de Entrada'!$C$2:$C$500, B16, 'Stock de Entrada'!$D$2:$D$500) -> 0 | E16: =SUMIF('Stock de Vendidos'!$C$2:$C$500, B16, 'Stock de Vendidos'!$D$2:$D$500) -> 0 | F16: =D16-E16 -> 0 | G16: =SUMIF('Stock de Entrada'!$C$2:$C$500, B16, 'Stock de Entrada'!$I$2:$I$500) -> 0 | H16: =SUMIF('Stock de Vendidos'!$C$2:$C$500, B16, 'Stock de Vendidos'!$I$2:$I$500) -> 0 | I16: =IF(D16>0, H16 - (E16 * (G16 / D16)), 0) -> 0 | J16: =IF(F16<=0, "Agotado", IF(F16<=3, "Stock Bajo", "Disponible")) -> Agotado
B17: ='Catálogo'!A11 -> iPhone 14 Pro Max | C17: ='Catálogo'!B11 -> Serie 14 Pro | D17: =SUMIF('Stock de Entrada'!$C$2:$C$500, B17, 'Stock de Entrada'!$D$2:$D$500) -> 0 | E17: =SUMIF('Stock de Vendidos'!$C$2:$C$500, B17, 'Stock de Vendidos'!$D$2:$D$500) -> 0 | F17: =D17-E17 -> 0 | G17: =SUMIF('Stock de Entrada'!$C$2:$C$500, B17, 'Stock de Entrada'!$I$2:$I$500) -> 0 | H17: =SUMIF('Stock de Vendidos'!$C$2:$C$500, B17, 'Stock de Vendidos'!$I$2:$I$500) -> 0 | I17: =IF(D17>0, H17 - (E17 * (G17 / D17)), 0) -> 0 | J17: =IF(F17<=0, "Agotado", IF(F17<=3, "Stock Bajo", "Disponible")) -> Agotado
B18: ='Catálogo'!A12 -> iPhone 14 Pro | C18: ='Catálogo'!B12 -> Serie 14 Pro | D18: =SUMIF('Stock de Entrada'!$C$2:$C$500, B18, 'Stock de Entrada'!$D$2:$D$500) -> 0 | E18: =SUMIF('Stock de Vendidos'!$C$2:$C$500, B18, 'Stock de Vendidos'!$D$2:$D$500) -> 0 | F18: =D18-E18 -> 0 | G18: =SUMIF('Stock de Entrada'!$C$2:$C$500, B18, 'Stock de Entrada'!$I$2:$I$500) -> 0 | H18: =SUMIF('Stock de Vendidos'!$C$2:$C$500, B18, 'Stock de Vendidos'!$I$2:$I$500) -> 0 | I18: =IF(D18>0, H18 - (E18 * (G18 / D18)), 0) -> 0 | J18: =IF(F18<=0, "Agotado", IF(F18<=3, "Stock Bajo", "Disponible")) -> Agotado
B19: ='Catálogo'!A13 -> iPhone 14 Plus | C19: ='Catálogo'!B13 -> Serie 14 Estándar | D19: =SUMIF('Stock de Entrada'!$C$2:$C$500, B19, 'Stock de Entrada'!$D$2:$D$500) -> 0 | E19: =SUMIF('Stock de Vendidos'!$C$2:$C$500, B19, 'Stock de Vendidos'!$D$2:$D$500) -> 0 | F19: =D19-E19 -> 0 | G19: =SUMIF('Stock de Entrada'!$C$2:$C$500, B19, 'Stock de Entrada'!$I$2:$I$500) -> 0 | H19: =SUMIF('Stock de Vendidos'!$C$2:$C$500, B19, 'Stock de Vendidos'!$I$2:$I$500) -> 0 | I19: =IF(D19>0, H19 - (E19 * (G19 / D19)), 0) -> 0 | J19: =IF(F19<=0, "Agotado", IF(F19<=3, "Stock Bajo", "Disponible")) -> Agotado
... B33: ='Catálogo'!A27 -> iPhone SE (2.ª gen) | C33: ='Catálogo'!B27 -> Serie SE | D33: =SUMIF('Stock de Entrada'!$C$2:$C$500, B33, 'Stock de Entrada'!$D$2:$D$500) -> 0 | E33: =SUMIF('Stock de Vendidos'!$C$2:$C$500, B33, 'Stock de Vendidos'!$D$2:$D$500) -> 0 | F33: =D33-E33 -> 0 | G33: =SUMIF('Stock de Entrada'!$C$2:$C$500, B33, 'Stock de Entrada'!$I$2:$I$500) -> 0 | H33: =SUMIF('Stock de Vendidos'!$C$2:$C$500, B33, 'Stock de Vendidos'!$I$2:$I$500) -> 0 | I33: =IF(D33>0, H33 - (E33 * (G33 / D33)), 0) -> 0 | J33: =IF(F33<=0, "Agotado", IF(F33<=3, "Stock Bajo", "Disponible")) -> Agotado
B34: TOTAL GENERAL | D34: =SUM(D8:D33) -> 0 | E34: =SUM(E8:E33) -> 0 | F34: =SUM(F8:F33) -> 0 | G34: =SUM(G8:G33) -> 0 | H34: =SUM(H8:H33) -> 0 | I34: =SUM(I8:I33) -> 0

Sheet Catálogo
A1: Producto | B1: Categoría
A2: iPhone 16 Pro Max | B2: Serie 16 Pro
A3: iPhone 16 Pro | B3: Serie 16 Pro
A4: iPhone 16 Plus | B4: Serie 16 Estándar
A5: iPhone 16 | B5: Serie 16 Estándar
A6: iPhone 16e | B6: Serie 16 Estándar
A7: iPhone 15 Pro Max | B7: Serie 15 Pro
A8: iPhone 15 Pro | B8: Serie 15 Pro
A9: iPhone 15 Plus | B9: Serie 15 Estándar
A10: iPhone 15 | B10: Serie 15 Estándar
A11: iPhone 14 Pro Max | B11: Serie 14 Pro
A12: iPhone 14 Pro | B12: Serie 14 Pro
... A32: Auriculares Inalambricos | B32: Airpods

Sheet Stock de Entrada
A1: ID Entrada | B1: Fecha | C1: Producto | D1: Cantidad | E1: Aplica Tasa | F1: Tasa BCV | G1: Costo Unitario (Bs.) | H1: Costo Unitario ($) | I1: Costo Total ($)
A2: =IF(ISBLANK(C2), "", "ENT-" & TEXT(ROW()-1, "0000")) | E2: FALSE | I2: =IF(OR(D2="", H2=""), "", D2*H2)
A3: =IF(ISBLANK(C3), "", "ENT-" & TEXT(ROW()-1, "0000")) | E3: FALSE | I3: =IF(OR(D3="", H3=""), "", D3*H3)
A4: =IF(ISBLANK(C4), "", "ENT-" & TEXT(ROW()-1, "0000")) | E4: FALSE | I4: =IF(OR(D4="", H4=""), "", D4*H4)
A5: =IF(ISBLANK(C5), "", "ENT-" & TEXT(ROW()-1, "0000")) | E5: FALSE | I5: =IF(OR(D5="", H5=""), "", D5*H5)
A6: =IF(ISBLANK(C6), "", "ENT-" & TEXT(ROW()-1, "0000")) | E6: FALSE | I6: =IF(OR(D6="", H6=""), "", D6*H6)
A7: =IF(ISBLANK(C7), "", "ENT-" & TEXT(ROW()-1, "0000")) | E7: FALSE | I7: =IF(OR(D7="", H7=""), "", D7*H7)
A8: =IF(ISBLANK(C8), "", "ENT-" & TEXT(ROW()-1, "0000")) | E8: FALSE | I8: =IF(OR(D8="", H8=""), "", D8*H8)
A9: =IF(ISBLANK(C9), "", "ENT-" & TEXT(ROW()-1, "0000")) | E9: FALSE | I9: =IF(OR(D9="", H9=""), "", D9*H9)
A10: =IF(ISBLANK(C10), "", "ENT-" & TEXT(ROW()-1, "0000")) | E10: FALSE | I10: =IF(OR(D10="", H10=""), "", D10*H10)
A11: =IF(ISBLANK(C11), "", "ENT-" & TEXT(ROW()-1, "0000")) | E11: FALSE | I11: =IF(OR(D11="", H11=""), "", D11*H11)
A12: =IF(ISBLANK(C12), "", "ENT-" & TEXT(ROW()-1, "0000")) | E12: FALSE | I12: =IF(OR(D12="", H12=""), "", D12*H12)
E13: FALSE
E14: FALSE
E15: FALSE
E16: FALSE
E17: FALSE
E18: FALSE
E19: FALSE
E20: FALSE
E21: FALSE
E22: FALSE
E23: FALSE
E24: FALSE
... E100: FALSE

Sheet Stock de Vendidos
A1: ID Venta | B1: Fecha | C1: Producto | D1: Cantidad | E1: Aplica Tasa | F1: Tasa BCV | G1: Precio Unitario (Bs.) | H1: Precio Unitario ($) | I1: Total Venta ($)
A2: =IF(ISBLANK(C2), "", "VNT-" & TEXT(ROW()-1, "0000")) | E2: FALSE | I2: =IF(OR(D2="", H2=""), "", D2*H2)
A3: =IF(ISBLANK(C3), "", "VNT-" & TEXT(ROW()-1, "0000")) | E3: FALSE | I3: =IF(OR(D3="", H3=""), "", D3*H3)
A4: =IF(ISBLANK(C4), "", "VNT-" & TEXT(ROW()-1, "0000")) | E4: FALSE | I4: =IF(OR(D4="", H4=""), "", D4*H4)
A5: =IF(ISBLANK(C5), "", "VNT-" & TEXT(ROW()-1, "0000")) | E5: FALSE | I5: =IF(OR(D5="", H5=""), "", D5*H5)
A6: =IF(ISBLANK(C6), "", "VNT-" & TEXT(ROW()-1, "0000")) | E6: FALSE | I6: =IF(OR(D6="", H6=""), "", D6*H6)
A7: =IF(ISBLANK(C7), "", "VNT-" & TEXT(ROW()-1, "0000")) | E7: FALSE | I7: =IF(OR(D7="", H7=""), "", D7*H7)
A8: =IF(ISBLANK(C8), "", "VNT-" & TEXT(ROW()-1, "0000")) | E8: FALSE | I8: =IF(OR(D8="", H8=""), "", D8*H8)
A9: =IF(ISBLANK(C9), "", "VNT-" & TEXT(ROW()-1, "0000")) | E9: FALSE | I9: =IF(OR(D9="", H9=""), "", D9*H9)
A10: =IF(ISBLANK(C10), "", "VNT-" & TEXT(ROW()-1, "0000")) | E10: FALSE | I10: =IF(OR(D10="", H10=""), "", D10*H10)
A11: =IF(ISBLANK(C11), "", "VNT-" & TEXT(ROW()-1, "0000")) | E11: FALSE | I11: =IF(OR(D11="", H11=""), "", D11*H11)
A12: =IF(ISBLANK(C12), "", "VNT-" & TEXT(ROW()-1, "0000")) | E12: FALSE | I12: =IF(OR(D12="", H12=""), "", D12*H12)
E13: FALSE
E14: FALSE
E15: FALSE
E16: FALSE
E17: FALSE
E18: FALSE
E19: FALSE
E20: FALSE
E21: FALSE
E22: FALSE
E23: FALSE
E24: FALSE
... E100: FALSE
